dnest4/__init__.py
dnest4/_dnest4.so
dnest4/analysis.py
dnest4/backends.py
dnest4/builder.py
dnest4/classic.py
dnest4/deprecated.py
dnest4/distributions.py
dnest4/loading.py
dnest4/sampler.py
dnest4/utils.so
dnest4-0.2.4.dist-info/LICENSE
dnest4-0.2.4.dist-info/METADATA
dnest4-0.2.4.dist-info/WHEEL
dnest4-0.2.4.dist-info/top_level.txt
dnest4-0.2.4.dist-info/RECORD
