Metadata-Version: 2.1
Name: dnest4
Version: 0.2.4
Summary: Diffusive nested sampling in Python
Home-page: https://github.com/eggplantbren/DNest4
Author: Daniel Foreman-Mackey
Author-email: foreman.mackey@gmail.com
License: MIT
Platform: UNKNOWN
Classifier: Intended Audience :: Developers
Classifier: Intended Audience :: Science/Research
Classifier: License :: OSI Approved :: MIT License
Classifier: Operating System :: OS Independent
Classifier: Programming Language :: Python
